CellTracker/__init__.py
CellTracker/analyses.py
CellTracker/coord_image_transformer.py
CellTracker/ffn.py
CellTracker/preprocess.py
CellTracker/stardist3dcustom.py
CellTracker/stardistwrapper.py
CellTracker/synthesize.py
CellTracker/track.py
CellTracker/tracker.py
CellTracker/trackerlite.py
CellTracker/unet3d.py
CellTracker/watershed.py
3deecelltracker-1.0.1.dist-info/LICENSE
3deecelltracker-1.0.1.dist-info/METADATA
3deecelltracker-1.0.1.dist-info/WHEEL
3deecelltracker-1.0.1.dist-info/RECORD
