Metadata-Version: 2.1
Name: 3DeeCellTracker
Version: 1.0.1
Summary: A 3D cell tracking tool for deforming organs or moving animals
License: MIT
Author: Chentao Wen
Author-email: chintou.on@gmail.com
Requires-Python: >=3.10,<3.11
Classifier: License :: OSI Approved :: MIT License
Classifier: Programming Language :: Python :: 3
Classifier: Programming Language :: Python :: 3.10
Requires-Dist: h5py (>=3.12.1,<4.0.0)
Requires-Dist: numpy (>=1.22,<2.0)
Requires-Dist: pillow (>=11.0,<12.0)
Requires-Dist: scikit-image (>=0.22,<0.23)
Requires-Dist: scikit-learn (>=1.5.2,<2.0.0)
Requires-Dist: scipy (>=1.11.4,<2.0.0)
Requires-Dist: tifffile (>=2024.9.20,<2025.0.0)
Requires-Dist: tqdm (>=4.67.1,<5.0.0)
